rtmodel-3.1.dist-info/RECORD
rtmodel-3.1.dist-info/METADATA
rtmodel-3.1.dist-info/WHEEL
rtmodel-3.1.dist-info/licenses/LICENSE
RTModel/RTModel.py
RTModel/__init__.py
RTModel/bin/InitCond
RTModel/bin/Finalizer
RTModel/bin/ModelSelector
RTModel/bin/LevMar
RTModel/bin/Reader
RTModel/data/TemplateLibrary.txt
RTModel/data/SunEphemeris.txt
RTModel/data/ESPL.tbl
RTModel/templates/templates.py
RTModel/templates/__init__.py
RTModel/plotmodel/plotmodel.py
RTModel/plotmodel/__init__.py
RTModel/include/LevMarFit.h
RTModel/include/bumper.h
RTModel/lib/ModelSelector.cpp
RTModel/lib/LevMar.cpp
RTModel/lib/Finalizer.cpp
RTModel/lib/Reader.cpp
RTModel/lib/bumper.cpp
RTModel/lib/InitCond.cpp
RTModel/lib/LevMarFit.cpp
