Metadata-Version: 2.1
Name: RTModel
Version: 3.1
Summary: RTModel is a tool for microlensing event interpretation.
Keywords: Microlensing analysis and fitting
Author-Email: Valerio Bozza <valboz@sa.infn.it>
License: GPL-3.0
Classifier: Development Status :: 5 - Production/Stable
Classifier: Intended Audience :: Science/Research
Classifier: License :: OSI Approved :: GNU Lesser General Public License v3 (LGPLv3)
Classifier: Programming Language :: Python :: 3
Project-URL: Homepage, https://github.com/valboz/RTModel
Requires-Python: <4,>=3.7
Requires-Dist: numpy
Requires-Dist: pytest
Requires-Dist: matplotlib
Requires-Dist: tqdm
Requires-Dist: tabulate
Requires-Dist: VBMicrolensing>=5.0
